fernet_wrapper/__init__.py
python_cryptography_fernet_wrapper-1.0.4.dist-info/LICENSE
python_cryptography_fernet_wrapper-1.0.4.dist-info/METADATA
python_cryptography_fernet_wrapper-1.0.4.dist-info/WHEEL
python_cryptography_fernet_wrapper-1.0.4.dist-info/top_level.txt
python_cryptography_fernet_wrapper-1.0.4.dist-info/RECORD
