Metadata-Version: 2.1
Name: python-cryptography-fernet-wrapper
Version: 1.0.4
Summary: A wrapper for cryptography.fernet
Home-page: https://github.com/KrazyKirby99999/python-cryptography-fernet-wrapper
Author: krazykirby99999
License: UNKNOWN
Platform: UNKNOWN
Classifier: Programming Language :: Python :: 3
Classifier: License :: OSI Approved :: GNU General Public License v3 (GPLv3)
Classifier: Operating System :: OS Independent
Requires-Python: >=3.6
License-File: LICENSE
